[{"content":"Markdown Blockquote “Totus mundus agit histrionem. (All the World\u0026rsquo;s a Stage.)\u0026quot;\n― William Shakespeare\u0026#39;s Globe Theatre Ordered List First item Second item Third item Unordered List List item Another item And another item Tables Name Age Bob 27 Alice 23 Code Blocks 1 2 3 4 5 6 #include \u0026lt;stdio.h\u0026gt; int main() { printf(\u0026#34;Hello world\u0026#34;); return 0; } Math This is an inline equation: $e^{i\\pi}+1=0$\nThis is a block equation: $$ t\u0026rsquo; = \\frac{t}{\\sqrt{1 - \\frac{v^2}{c^2}}} $$\nMedia Image Video ","date":"2023-11-10T00:00:00+08:00","image":"https://ntaquan0125.github.io/p/hello-world/cover_hud7e36f7e20e71be184458283bdae4646_55974_120x120_fill_q75_box_smart1.jpg","permalink":"https://ntaquan0125.github.io/p/hello-world/","title":"Hello World!"}]